huaweicloudsdkhss/__init__.py
huaweicloudsdkhss/v5/__init__.py
huaweicloudsdkhss/v5/hss_async_client.py
huaweicloudsdkhss/v5/hss_client.py
huaweicloudsdkhss/v5/model/__init__.py
huaweicloudsdkhss/v5/model/account_response_info.py
huaweicloudsdkhss/v5/model/action.py
huaweicloudsdkhss/v5/model/add_accounts_request_info.py
huaweicloudsdkhss/v5/model/add_app_whitelist_policy_host_request.py
huaweicloudsdkhss/v5/model/add_app_whitelist_policy_host_request_info.py
huaweicloudsdkhss/v5/model/add_app_whitelist_policy_host_response.py
huaweicloudsdkhss/v5/model/add_app_whitelist_policy_process_info.py
huaweicloudsdkhss/v5/model/add_app_whitelist_policy_process_request.py
huaweicloudsdkhss/v5/model/add_app_whitelist_policy_process_request_info.py
huaweicloudsdkhss/v5/model/add_app_whitelist_policy_process_response.py
huaweicloudsdkhss/v5/model/add_baseline_white_list_request.py
huaweicloudsdkhss/v5/model/add_baseline_white_list_request_body.py
huaweicloudsdkhss/v5/model/add_baseline_white_list_request_body_rule_list.py
huaweicloudsdkhss/v5/model/add_baseline_white_list_response.py
huaweicloudsdkhss/v5/model/add_cce_integration_protection_request.py
huaweicloudsdkhss/v5/model/add_cce_integration_protection_response.py
huaweicloudsdkhss/v5/model/add_cicd_configuration_request.py
huaweicloudsdkhss/v5/model/add_cicd_configuration_request_body.py
huaweicloudsdkhss/v5/model/add_cicd_configuration_response.py
huaweicloudsdkhss/v5/model/add_hosts_group_request.py
huaweicloudsdkhss/v5/model/add_hosts_group_request_info.py
huaweicloudsdkhss/v5/model/add_hosts_group_response.py
huaweicloudsdkhss/v5/model/add_image_white_lists_request.py
huaweicloudsdkhss/v5/model/add_image_white_lists_request_body.py
huaweicloudsdkhss/v5/model/add_image_white_lists_request_body_image_info.py
huaweicloudsdkhss/v5/model/add_image_white_lists_request_body_query_info.py
huaweicloudsdkhss/v5/model/add_image_white_lists_response.py
huaweicloudsdkhss/v5/model/add_login_white_list_request.py
huaweicloudsdkhss-3.1.172.dist-info/METADATA
huaweicloudsdkhss-3.1.172.dist-info/WHEEL
huaweicloudsdkhss-3.1.172.dist-info/licenses/LICENSE
huaweicloudsdkhss-3.1.172.dist-info/RECORD
